setup.py
eyaml/__init__.py
eyaml.egg-info/PKG-INFO
eyaml.egg-info/SOURCES.txt
eyaml.egg-info/dependency_links.txt
eyaml.egg-info/requires.txt
eyaml.egg-info/top_level.txt