Metadata-Version: 1.1
Name: eyaml
Version: 0.1
Summary: Thin Wrapper around PyYAML with env support
Home-page: http://www.bryanmarty.com/
Author: Bryan Marty
Author-email: bryan@bryanmarty.com
License: MIT
Keywords: yaml env environment
Platform: UNKNOWN
Classifier: Development Status :: 3 - Alpha
Classifier: Topic :: Utilities
Classifier: License :: OSI Approved :: MIT License
